CHANGES.txt
LICENSE.txt
README.txt
bootstrap.py
buildout.cfg
setup.py
src/getpaid/__init__.py
src/getpaid.paymentech.egg-info/PKG-INFO
src/getpaid.paymentech.egg-info/SOURCES.txt
src/getpaid.paymentech.egg-info/dependency_links.txt
src/getpaid.paymentech.egg-info/namespace_packages.txt
src/getpaid.paymentech.egg-info/not-zip-safe
src/getpaid.paymentech.egg-info/requires.txt
src/getpaid.paymentech.egg-info/top_level.txt
src/getpaid/paymentech/README.txt
src/getpaid/paymentech/__init__.py
src/getpaid/paymentech/configure.zcml
src/getpaid/paymentech/interfaces.py
src/getpaid/paymentech/paymentech.py