Metadata-Version: 1.0
Name: getpaid.paymentech
Version: 0.3
Summary: Get paid paymentech payment processor functionality
Home-page: http://code.google.com/p/getpaid
Author: Six Feet Up, Inc.
Author-email: getpaid-dev@googlegroups.com
License: ZPL2.1
Platform: UNKNOWN
Classifier: Framework :: Plone
Classifier: Programming Language :: Python
Classifier: Framework :: Zope3
Classifier: Intended Audience :: Developers
Classifier: License :: OSI Approved :: Zope Public License
Classifier: Operating System :: OS Independent
Classifier: Topic :: Office/Business :: Financial
Classifier: Topic :: Software Development :: Libraries
